opendal_min-0.45.2.dist-info/METADATA
opendal_min-0.45.2.dist-info/WHEEL
opendal/exceptions.pyi
opendal/layers.pyi
opendal/__init__.py
opendal/__init__.pyi
opendal/_opendal.cp310-win32.pyd
opendal_min-0.45.2.dist-info/RECORD
