Metadata-Version: 2.3
Name: opendal-min
Version: 0.45.2
Classifier: Programming Language :: Rust
Classifier: Programming Language :: Python :: Implementation :: CPython
Classifier: Programming Language :: Python :: Implementation :: PyPy
Requires-Dist: gevent ; extra == 'benchmark'
Requires-Dist: greenify ; extra == 'benchmark'
Requires-Dist: greenlet ; extra == 'benchmark'
Requires-Dist: boto3 ; extra == 'benchmark'
Requires-Dist: pydantic ; extra == 'benchmark'
Requires-Dist: boto3-stubs[essential] ; extra == 'benchmark'
Requires-Dist: pdoc ; extra == 'docs'
Requires-Dist: ruff ; extra == 'lint'
Requires-Dist: pytest ; extra == 'test'
Requires-Dist: python-dotenv ; extra == 'test'
Requires-Dist: pytest-asyncio ; extra == 'test'
Provides-Extra: benchmark
Provides-Extra: docs
Provides-Extra: lint
Provides-Extra: test
Summary: Apache OpenDAL™ Python Binding
Home-Page: https://opendal.apache.org/
Author: Apache OpenDAL <dev@opendal.apache.org>
Author-email: Apache OpenDAL <dev@opendal.apache.org>
License: Apache-2.0
Requires-Python: >=3.7, <3.13
Project-URL: Documentation, https://opendal.apache.org/docs/python/opendal.html
Project-URL: Homepage, https://opendal.apache.org/
Project-URL: Repository, https://github.com/apache/opendal
